miningpy/VERSION
miningpy/__init__.py
miningpy/core/__init__.py
miningpy/core/core.py
miningpy/utilities/__init__.py
miningpy/utilities/export_vtkjs.py
miningpy/utilities/numpy_vtk.py
miningpy/visualisation/ParaViewGlance.html
miningpy/visualisation/__init__.py
miningpy/visualisation/block_model_plot.py
miningpy/visualisation/core.py
miningpy/visualisation/dxf.py
miningpy/visualisation/export_html.py
miningpy/vulcan/__init__.py
miningpy/vulcan/core.py
miningpy/whittle/__init__.py
miningpy/whittle/core.py
miningpy-0.6.4.dist-info/LICENSE
miningpy-0.6.4.dist-info/METADATA
miningpy-0.6.4.dist-info/WHEEL
miningpy-0.6.4.dist-info/top_level.txt
miningpy-0.6.4.dist-info/RECORD
