Metadata-Version: 2.1
Name: miningpy
Version: 0.6.4
Summary: python tools for mining engineering
Home-page: 
Author: Iain Fullelove
Author-email: fullelove.iain@gmail.com
Classifier: Programming Language :: Python :: 3
Classifier: Development Status :: 3 - Alpha
Classifier: Natural Language :: English
Classifier: Operating System :: Microsoft :: Windows
Classifier: License :: OSI Approved :: MIT License
License-File: LICENSE
Requires-Dist: ezdxf >=1.0
Requires-Dist: pandas >=2.1
Requires-Dist: numpy >=1.26
Requires-Dist: pyvista >=0.43
Requires-Dist: pyvistaqt
Requires-Dist: pyqt5
Requires-Dist: vtk >=9.2
Requires-Dist: matplotlib
